metronome/__init__.py
metronome/_base_client.py
metronome/_client.py
metronome/_compat.py
metronome/_constants.py
metronome/_exceptions.py
metronome/_files.py
metronome/_models.py
metronome/_qs.py
metronome/_resource.py
metronome/_response.py
metronome/_streaming.py
metronome/_types.py
metronome/_version.py
metronome/pagination.py
metronome/py.typed
metronome/_utils/__init__.py
metronome/_utils/_compat.py
metronome/_utils/_datetime_parse.py
metronome/_utils/_logs.py
metronome/_utils/_proxy.py
metronome/_utils/_reflection.py
metronome/_utils/_resources_proxy.py
metronome/_utils/_streams.py
metronome/_utils/_sync.py
metronome/_utils/_transform.py
metronome/_utils/_typing.py
metronome/_utils/_utils.py
metronome/lib/.keep
metronome/resources/__init__.py
metronome/resources/v1/__init__.py
metronome/resources/v1/alerts.py
metronome/resources/v1/audit_logs.py
metronome/resources/v1/billable_metrics.py
metronome/resources/v1/credit_grants.py
metronome/resources/v1/custom_fields.py
metronome/resources/v1/dashboards.py
metronome/resources/v1/invoices.py
metronome/resources/v1/payments.py
metronome/resources/v1/plans.py
metronome/resources/v1/pricing_units.py
metronome/resources/v1/services.py
metronome/resources/v1/usage.py
metronome/resources/v1/v1.py
metronome/resources/v1/contracts/__init__.py
metronome/resources/v1/contracts/contracts.py
metronome/resources/v1/contracts/named_schedules.py
metronome/resources/v1/contracts/products.py
metronome/resources/v1/contracts/rate_cards/__init__.py
metronome/resources/v1/contracts/rate_cards/named_schedules.py
metronome/resources/v1/contracts/rate_cards/product_orders.py
metronome/resources/v1/contracts/rate_cards/rate_cards.py
metronome/resources/v1/contracts/rate_cards/rates.py
metronome/resources/v1/customers/__init__.py
metronome/resources/v1/customers/alerts.py
metronome/resources/v1/customers/billing_config.py
metronome/resources/v1/customers/commits.py
metronome/resources/v1/customers/credits.py
metronome_sdk-4.0.0.dist-info/METADATA
metronome_sdk-4.0.0.dist-info/WHEEL
metronome_sdk-4.0.0.dist-info/licenses/LICENSE
metronome_sdk-4.0.0.dist-info/RECORD
